LICENSE
MANIFEST.in
README.rst
setup.cfg
setup.py
versioneer.py
artellapipe/__init__.py
artellapipe/tools/__init__.py
artellapipe/tools/artellamanager/__init__.py
artellapipe/tools/artellamanager/__logging__.ini
artellapipe/tools/artellamanager/__version__.py
artellapipe/tools/artellamanager/_version.py
artellapipe/tools/artellamanager/core/__init__.py
artellapipe/tools/artellamanager/core/artellamanager.py
artellapipe/tools/artellamanager/resources/images/artellamanager_logo.png
artellapipe/tools/artellamanager/resources/images/no_assets_found.png
artellapipe/tools/artellamanager/resources/images/sync_no_items.png
artellapipe/tools/artellamanager/widgets/__init__.py
artellapipe/tools/artellamanager/widgets/artellamanagertool.py
artellapipe/tools/artellamanager/widgets/artellamanagerwidget.py
artellapipe/tools/artellamanager/widgets/filestree.py
artellapipe/tools/artellamanager/widgets/folderstree.py
artellapipe/tools/artellamanager/widgets/loading.py
artellapipe/tools/artellamanager/widgets/workers.py
artellapipe_tools_artellamanager.egg-info/PKG-INFO
artellapipe_tools_artellamanager.egg-info/SOURCES.txt
artellapipe_tools_artellamanager.egg-info/dependency_links.txt
artellapipe_tools_artellamanager.egg-info/not-zip-safe
artellapipe_tools_artellamanager.egg-info/requires.txt
artellapipe_tools_artellamanager.egg-info/top_level.txt
tests/__init__.py
tests/test_general.py