Metadata-Version: 2.1
Name: artellapipe-tools-artellamanager
Version: 0.0.13
Summary: Tool to manage Artella server and local files
Home-page: https://github.com/ArtellaPipe/artellapipe-tools-artellamanager
Author: Tomas Poveda
Author-email: tpovedatd@gmail.com
License: MIT
Platform: UNKNOWN
Provides-Extra: dev
Provides-Extra: test
